nwn/__init__.py
nwn/_shared.py
nwn/compressedbuf.py
nwn/erf.py
nwn/key.py
nwn/ssf.py
nwn/tileset.py
nwn/tlk.py
nwn/twoda.py
nwn/gff/__init__.py
nwn/gff/_impl.py
nwn/gff/_json.py
nwn/gff/_reader.py
nwn/gff/_types.py
nwn/gff/_writer.py
nwn/nwscript/__init__.py
nwn/nwscript/_types.py
nwn/nwscript/asm.py
nwn/nwscript/comp.py
nwn/nwscript/langspec.py
nwn/nwscript/ndb.py
nwn/nwscript/lib/README.txt
nwn/nwscript/lib/linux_aarch64/libnwnscriptcomp.so
nwn/nwscript/lib/linux_x86_64/libnwnscriptcomp.so
nwn/nwscript/lib/macos_aarch64/libnwnscriptcomp.dylib
nwn/nwscript/lib/macos_x86_64/libnwnscriptcomp.dylib
nwn/nwscript/lib/windows_aarch64/libnwnscriptcomp.dll
nwn/nwscript/lib/windows_x86_64/libnwnscriptcomp.dll
nwn/nwscript/vm/__init__.py
nwn/nwscript/vm/_script.py
nwn/nwscript/vm/_stack.py
nwn/nwscript/vm/_vm.py
nwn/nwsync/__init__.py
nwn/nwsync/manifest.py
nwn-0.0.18.dist-info/METADATA
nwn-0.0.18.dist-info/WHEEL
nwn-0.0.18.dist-info/licenses/LICENSE
nwn-0.0.18.dist-info/RECORD
