Metadata-Version: 2.4
Name: nwn
Version: 0.0.18
Summary: collection of modules for working with Neverwinter Nights 1: Enhanced Edition
Project-URL: Source Code, https://github.com/niv/nwn.py
Project-URL: Issue Tracker, https://github.com/niv/nwn.py/issues
Project-URL: Documentation, https://niv.github.io/nwn.py/
Author-email: Bernhard Stoeckner <n@e-ix.net>
License-Expression: MIT
License-File: LICENSE
Classifier: Development Status :: 3 - Alpha
Classifier: License :: OSI Approved :: MIT License
Classifier: Programming Language :: Python :: 3 :: Only
Classifier: Topic :: Games/Entertainment :: Role-Playing
Requires-Python: >=3.10
Requires-Dist: pyzstd>=0.16.2
